Metadata-Version: 2.1
Name: isimud
Version: 0.2
Summary: Package to get commonly used details of the network interface and access points you are using..
Home-page: https://github.com/carlosplanchon/isimud
Author: Carlos A. Planchón
Author-email: bubbledoloresuruguay2@gmail.com
License: GPL3
Download-URL: https://github.com/carlosplanchon/isimud/archive/v0.2.tar.gz
Keywords: isimud,sensors,wifi,networking
Platform: UNKNOWN
Classifier: Intended Audience :: Developers
Classifier: Topic :: Software Development :: Build Tools
Classifier: License :: OSI Approved :: GNU General Public License v3 (GPLv3)
Classifier: Programming Language :: Python :: 3
Classifier: Programming Language :: Python :: 3.4
Classifier: Programming Language :: Python :: 3.5
Classifier: Programming Language :: Python :: 3.6
Classifier: Programming Language :: Python :: 3.7
